turbo_agent_core/__init__.py
turbo_agent_core/schema/__init__.py
turbo_agent_core/schema/agents.py
turbo_agent_core/schema/basic.py
turbo_agent_core/schema/enums.py
turbo_agent_core/schema/events.py
turbo_agent_core/schema/external.py
turbo_agent_core/schema/jobs.py
turbo_agent_core/schema/refs.py
turbo_agent_core/schema/resources.py
turbo_agent_core/schema/states.py
turbo_agent_core/schema/event_utils/builders.py
turbo_agent_core/utils/aggregators.py
turbo_agent_core/utils/analyze_json.py
turbo_agent_core/utils/event_integrator.py
turbo_agent_core/utils/grid_layout_calculator.py
turbo_agent_core/utils/identity.py
turbo_agent_core/utils/json_assembler.py
turbo_agent_core/utils/json_stream.py
turbo_agent_core/utils/param_schema.py
turbo_agent_core/utils/schema_tool.py
turbo_agent_core/utils/trace_event_aggregator.py
turbo_agent_core-0.1.0.dist-info/METADATA
turbo_agent_core-0.1.0.dist-info/WHEEL
turbo_agent_core-0.1.0.dist-info/RECORD
