Metadata-Version: 2.4
Name: turbo-agent-core
Version: 0.1.0
Summary: Core utilities and shared types for turbo-agent
Project-URL: Homepage, https://example.com/turbo-agent
Author-email: sherlet <wuzeilmt@gmail.com>
Requires-Python: <3.14,>=3.10
Requires-Dist: croniter>=6.0.0
Requires-Dist: pydantic>=2.0.0
Requires-Dist: typing-extensions>=4.15.0
